[
  {
    "title": "Community",
    "isExpanded": false,
    "links": [
      {
        "iconUrl": "/homepage/icons/icons8/web.png",
        "label": "Website",
        "url": "https://janus-idp.io/community"
      },
      {
        "iconUrl": "/homepage/icons/icons8/external-blog-copywriting-itim2101-lineal-itim2101.png",
        "label": "Blog",
        "url": "https://janus-idp.io/blog"
      },
      {
        "iconUrl": "/homepage/icons/icons8/github.png",
        "label": "GitHub",
        "url": "https://github.com/orgs/janus-idp"
      },
      {
        "iconUrl": "/homepage/icons/icons8/slack-new.png",
        "label": "Slack",
        "url": "https://join.slack.com/t/janus-idp/shared_invite/zt-1pxtehxom-fCFtF9rRe3vFqUiFFeAkmg"
      },
      {
        "iconUrl": "/homepage/icons/icons8/youtube-play.png",
        "label": "YouTube Channel",
        "url": "https://www.youtube.com/@januscommunity"
      },
      {
        "iconUrl": "/homepage/icons/icons8/external-mailing-list-information-technology-solid-solidglyph-m-oki-orlando.png",
        "label": "Mailing List",
        "url": "https://groups.google.com/g/janus-idp-community"
      },
      {
        "iconUrl": "/homepage/icons/icons8/tear-off-calendar.png",
        "label": "Calendar",
        "url": "https://calendar.google.com/calendar/u/0?cid=amFudXMuaWRwLmNvbW11bml0eUBnbWFpbC5jb20"
      }
    ]
  },
  {
    "title": "Developer Tools",
    "isExpanded": true,
    "links": [
      {
        "iconUrl": "/homepage/icons/podman_logo.svg",
        "label": "Podman Desktop",
        "url": "https://podman-desktop.io"
      }
    ]
  },
  {
    "title": "CI/CD Tools",
    "isExpanded": true,
    "links": [
      {
        "iconUrl": "/homepage/icons/argo-icon-color.svg",
        "label": "ArgoCD",
        "url": "https://argoproj.github.io/cd/"
      },
      {
        "iconUrl": "/homepage/icons/sonarqube.svg",
        "label": "SonarQube",
        "url": "https://www.sonarsource.com/open-source-editions/"
      },
      {
        "iconUrl": "/homepage/icons/quay.svg",
        "label": "Quay.io",
        "url": "https://quay.io/"
      }
    ]
  },
  {
    "title": "OpenShift Clusters",
    "isExpanded": true,
    "links": [
      {
        "iconUrl": "/homepage/icons/icons8/openshift.png",
        "label": "OpenShift",
        "url": "https://docs.openshift.com/"
      }
    ]
  },
  {
    "title": "Monitoring Tools",
    "links": [
      {
        "iconUrl": "/homepage/icons/icons8/system-task.png",
        "label": "Grafana",
        "url": "https://grafana.com/"
      }
    ]
  },
  {
    "title": "Security Tools",
    "links": [
      {
        "iconUrl": "/homepage/icons/icons8/security-checked.png",
        "label": "GitHub Security",
        "url": "https://docs.github.com/en/code-security"
      },
      {
        "iconUrl": "/homepage/icons/keycloak.svg",
        "label": "Keycloak",
        "url": "https://www.keycloak.org/"
      }
    ]
  }
]
